django_group_role/__init__.py
django_group_role/apps.py
django_group_role/exceptions.py
django_group_role/roles.py
django_group_role/signals.py
django_group_role/test.py
django_group_role/utils.py
django_group_role/management/__init__.py
django_group_role/management/commands/__init__.py
django_group_role/management/commands/populate_roles.py
django_group_role-0.7.4.dist-info/licenses/LICENSE
django_group_role-0.7.4.dist-info/METADATA
django_group_role-0.7.4.dist-info/WHEEL
django_group_role-0.7.4.dist-info/top_level.txt
django_group_role-0.7.4.dist-info/RECORD
